<experiment count="5">
  <!--DO NOT EDIT. File automatically generated by librec-auto-->
  <meta>
    <param>
      <name>lambda</name>
      <value>0.05</value>
    </param>
  </meta>
  <statuses>
    <status>
      <message>Executing</message>
      <exp_no>5</exp_no>
      <date>2022-08-11 05:04:03.267218</date>
    </status>
    <status>
      <message>Completed</message>
      <date>2022-08-11 05:05:29.751150</date>
    </status>
    <status>
      <message>Executing</message>
      <date>2022-08-11 08:59:40.201420</date>
    </status>
    <status>
      <message>Completed</message>
      <date>2022-08-11 08:59:53.552703</date>
    </status>
  </statuses>
  <results>
    <folds>
      <cv id="1">
        <metric name="NormalizedDCGEvaluator">0.06690685403974501</metric>
        <metric name="PStatisticalParityEvaluator">-0.75014042126384</metric>
        <metric name="ndcg_metric.py">0.06651141587236567</metric>
        <metric name="psp.py">-0.842570281124498</metric>
      </cv>
      <cv id="2">
        <metric name="NormalizedDCGEvaluator">0.06181613554368483</metric>
        <metric name="PStatisticalParityEvaluator">-0.7622991967872006</metric>
        <metric name="ndcg_metric.py">0.059130151808591526</metric>
        <metric name="psp.py">-0.8839388624404911</metric>
      </cv>
      <cv id="3">
        <metric name="NormalizedDCGEvaluator">0.05711707177258422</metric>
        <metric name="PStatisticalParityEvaluator">-0.7698822350288681</metric>
        <metric name="ndcg_metric.py">0.0716905466578318</metric>
        <metric name="psp.py">-0.7580742226680041</metric>
      </cv>
    </folds>
    <averages>
      <metric name="NormalizedDCGEvaluator">0.06194668711867135</metric>
      <metric name="PStatisticalParityEvaluator">-0.7607739510266361</metric>
      <metric name="ndcg_metric.py">0.065777371446263</metric>
      <metric name="psp.py">-0.8281944554109978</metric>
    </averages>
  </results>
</experiment>
